snAPI/__init__.py
snAPI/api.py
snAPI/cache.py
snAPI/sessions.py
pySnAPI-0.0.3.dist-info/LICENSE
pySnAPI-0.0.3.dist-info/METADATA
pySnAPI-0.0.3.dist-info/WHEEL
pySnAPI-0.0.3.dist-info/top_level.txt
pySnAPI-0.0.3.dist-info/RECORD
