Metadata-Version: 2.1
Name: pySnAPI
Version: 0.0.3
Summary: A package for speeding up API calls
Author-email: Mannan Bhardwaj <mannanb728@gmail.com>
License: MIT License
Project-URL: Homepage, https://github.com/MannanB/snAPI
Project-URL: Bug Tracker, https://github.com/MannanB/snAPI/issues
Classifier: Programming Language :: Python :: 3
Classifier: License :: OSI Approved :: MIT License
Classifier: Operating System :: OS Independent
Requires-Python: >=3.10
License-File: LICENSE
Requires-Dist: aiohttp
Requires-Dist: requests
